rustcfg/__init__.py
rustcfg/test/__init__.py
rustcfg/test/test_expressions.py
rustcfg-0.0.2.dist-info/LICENSE.txt
rustcfg-0.0.2.dist-info/METADATA
rustcfg-0.0.2.dist-info/RECORD
rustcfg-0.0.2.dist-info/WHEEL
rustcfg-0.0.2.dist-info/top_level.txt
